phycontrib/__init__.py
phycontrib/kwik_gui/__init__.py
phycontrib/kwik_gui/gui.py
phycontrib/kwik_gui/static/state.json
phycontrib/template/__init__.py
phycontrib/template/gui.py
phycontrib/template/model.py
phycontrib/template/static/state.json
phycontrib/utils/__init__.py
phycontrib/utils/precache.py
phycontrib/utils/saveprompt.py
phycontrib-1.0.15.dist-info/DESCRIPTION.rst
phycontrib-1.0.15.dist-info/METADATA
phycontrib-1.0.15.dist-info/RECORD
phycontrib-1.0.15.dist-info/WHEEL
phycontrib-1.0.15.dist-info/metadata.json
phycontrib-1.0.15.dist-info/top_level.txt
