Metadata-Version: 2.0
Name: phycontrib
Version: 1.0.15
Summary: Spike sorting and ephys data analysis for 1000 channels and beyond
Home-page: https://phy.cortexlab.net
Author: Kwik Team
Author-email: cyrille.rossant at gmail.com
License: BSD
Keywords: phy,data analysis,electrophysiology,neuroscience
Platform: UNKNOWN
Classifier: Development Status :: 4 - Beta
Classifier: Intended Audience :: Developers
Classifier: License :: OSI Approved :: BSD License
Classifier: Natural Language :: English
Classifier: Framework :: IPython
Classifier: Programming Language :: Python :: 2
Classifier: Programming Language :: Python :: 2.7
Classifier: Programming Language :: Python :: 3
Classifier: Programming Language :: Python :: 3.5
